setup.py
my_pkg/Hello.py
my_pkg/__init__.py
wkbk_package.egg-info/PKG-INFO
wkbk_package.egg-info/SOURCES.txt
wkbk_package.egg-info/dependency_links.txt
wkbk_package.egg-info/entry_points.txt
wkbk_package.egg-info/top_level.txt